LICENSE
MANIFEST.in
README.md
setup.cfg
setup.py
niemabf/BitArray.py
niemabf/BloomFilter.py
niemabf/Hash.py
niemabf/HashSet.py
niemabf/__init__.py
niemabf/common.py
niemabf.egg-info/PKG-INFO
niemabf.egg-info/SOURCES.txt
niemabf.egg-info/dependency_links.txt
niemabf.egg-info/requires.txt
niemabf.egg-info/top_level.txt